pancli/VERSION
pancli/__init__.py
pancli/cli.py
pancli/plugin.py
pancli/runner.py
pancli/runner2.py
pancli/util.py
pancli/commands/__init__.py
pancli/commands/crawl.py
pancli/commands/deploy.py
pancli/commands/list.py
pancli/commands/package.py
pancli/commands/plugin.py
pancli/commands/settings.py
pancli-0.1.9.dist-info/LICENSE
pancli-0.1.9.dist-info/METADATA
pancli-0.1.9.dist-info/WHEEL
pancli-0.1.9.dist-info/entry_points.txt
pancli-0.1.9.dist-info/top_level.txt
pancli-0.1.9.dist-info/RECORD
