Metadata-Version: 2.1
Name: pancli
Version: 0.1.9
Summary: pansihub command-line tools.
Home-page: https://github.com/pansihub/pancli
Author: kevenli
Author-email: pbleester@gmail.com
License: UNKNOWN
Platform: UNKNOWN
Requires-Dist: pyaml
Requires-Dist: requests
